version_number_increase.py
ChLT/Chinese_learn.py
ChLT/QGUI_widget.py
ChLT/__init__.py
ChLT/gif_play.py
ChLT/playsound.py
chinese_learning_tool-0.0.4.dist-info/METADATA
chinese_learning_tool-0.0.4.dist-info/WHEEL
chinese_learning_tool-0.0.4.dist-info/entry_points.txt
chinese_learning_tool-0.0.4.dist-info/license_files/LICENSE
chinese_learning_tool-0.0.4.dist-info/RECORD
