Metadata-Version: 2.1
Name: chinese-learning-tool
Version: 0.0.4
Summary: It is a tool to learn how to read and write Chinese Characters.
Project-URL: Bug Tracker, https://gitee.com/shawnyanwang/chinese-learning-tool/issues
Project-URL: Homepage, https://gitee.com/shawnyanwang/chinese-learning-tool
Author-email: shawn yan wang <shawnyanwang@gmail.com>
Classifier: License :: OSI Approved :: MIT License
Classifier: Operating System :: OS Independent
Classifier: Programming Language :: Python :: 3
Requires-Python: >=3.7
